pyspark_dataframe_wrappers/__init__.py
pyspark_dataframe_wrappers/test_dataframe.py
pyspark_dataframe_wrappers-0.1.5.dist-info/WHEEL
pyspark_dataframe_wrappers-0.1.5.dist-info/METADATA
pyspark_dataframe_wrappers-0.1.5.dist-info/RECORD
